backoff_utils/__init__.py
backoff_utils/_backoff.py
backoff_utils/_decorator.py
backoff_utils/_version.py
backoff_utils/strategies.py
backoff_utils-1.0.0.dist-info/LICENSE.txt
backoff_utils-1.0.0.dist-info/METADATA
backoff_utils-1.0.0.dist-info/RECORD
backoff_utils-1.0.0.dist-info/WHEEL
backoff_utils-1.0.0.dist-info/top_level.txt
